jhOMR_webInterface/OMRutils_v5.py
jhOMR_webInterface/OMRutils_v6.py
jhOMR_webInterface/__init__.py
jhOMR_webInterface/shuffle_tf_and_mcq_v7.py
jhOMR_webInterface/utils_Latex_Exam_Questions_Generator.py
jhOMR_webInterface/utils_Latex_create_update_question_bank.py
jhOMR_webInterface/utils_Scanned_Script_check.py
jhomr_webinterface-0.2.0.dist-info/METADATA
jhomr_webinterface-0.2.0.dist-info/WHEEL
jhomr_webinterface-0.2.0.dist-info/top_level.txt
jhomr_webinterface-0.2.0.dist-info/RECORD
